setup.py
bin/mabs
mabs/__init__.py
mabs/hosts_settings.py
mabs/mabs.py
mabs/test.py
mabs.egg-info/PKG-INFO
mabs.egg-info/SOURCES.txt
mabs.egg-info/dependency_links.txt
mabs.egg-info/requires.txt
mabs.egg-info/top_level.txt