Metadata-Version: 1.0
Name: mabs
Version: 0.1.2
Summary: used to control server by group with password,系统集中管理
Home-page: https://github.com/targetoyes/mabs
Author: targetoyes
Author-email: targetoyes@163.com
License: mabsvs License
Keywords: mabs,egg
Platform: any
